<?xml version="1.0" encoding="utf-8"?>
<!DOCTYPE hibernate-mapping PUBLIC "-//Hibernate/Hibernate Mapping DTD 3.0//EN"
"http://hibernate.sourceforge.net/hibernate-mapping-3.0.dtd">
<!-- 
    Mapping file autogenerated by MyEclipse Persistence Tools
-->
<hibernate-mapping>
    <class name="com.banshan.lifebarServer.model.TblTypeOfProduct" table="tbl_typeOfProduct" catalog="lifebar">
        <id name="id" type="java.lang.Long">
            <column name="Id" />
            <generator class="identity" />
        </id>
        <property name="productId" type="java.lang.Long">
            <column name="productId" not-null="true" />
        </property>
        <property name="typeId" type="java.lang.Integer">
            <column name="typeId" not-null="true" />
        </property>
    </class>
</hibernate-mapping>
